authtoken/__init__.py
authtoken/admin.py
authtoken/apps.py
authtoken/extensions.py
authtoken/models.py
authtoken/security.py
authtoken/signals.py
authtoken/tests.py
authtoken/migrations/0001_initial.py
authtoken/migrations/0002_remove_apikey_expires_at_remove_apikey_revoked.py
authtoken/migrations/0003_alter_apikey_user.py
authtoken/migrations/__init__.py
ninja_authtoken-1.0.1.dist-info/LICENSE
ninja_authtoken-1.0.1.dist-info/METADATA
ninja_authtoken-1.0.1.dist-info/WHEEL
ninja_authtoken-1.0.1.dist-info/top_level.txt
ninja_authtoken-1.0.1.dist-info/RECORD
