Metadata-Version: 2.1
Name: ninja-authtoken
Version: 1.0.1
Summary: A simple Django app for django-ninja authentication tokens
Home-page: https://github.com/MoriZoki/ninja-authtoken
Author: MoriZoki
Author-email: morizoki.django@gmail.com
Classifier: Programming Language :: Python :: 3
Classifier: Framework :: Django
Classifier: License :: OSI Approved :: MIT License
Classifier: Operating System :: OS Independent
Requires-Python: >=3.6
License-File: LICENSE
Requires-Dist: Django
Requires-Dist: django-ninja
